CHANGES.txt
CONTRIBUTORS.txt
README.txt
bootstrap.py
buildout.cfg
setup.py
gocept/__init__.py
gocept.recipe.env.egg-info/PKG-INFO
gocept.recipe.env.egg-info/SOURCES.txt
gocept.recipe.env.egg-info/dependency_links.txt
gocept.recipe.env.egg-info/entry_points.txt
gocept.recipe.env.egg-info/namespace_packages.txt
gocept.recipe.env.egg-info/not-zip-safe
gocept.recipe.env.egg-info/requires.txt
gocept.recipe.env.egg-info/top_level.txt
gocept/recipe/__init__.py
gocept/recipe/env/README.txt
gocept/recipe/env/__init__.py
gocept/recipe/env/tests/__init__.py
gocept/recipe/env/tests/test_docs.py
