Metadata-Version: 1.0
Name: gocept.recipe.env
Version: 1.0
Summary: Mirror environment variables into a buildout section.
Home-page: UNKNOWN
Author: Christian Theune
Author-email: ct@gocept.com
License: ZPL
Keywords: buildout
Platform: UNKNOWN
Classifier: Framework :: Buildout
Classifier: Intended Audience :: Developers
Classifier: Topic :: Software Development :: Build Tools
Classifier: Topic :: Software Development :: Libraries :: Python Modules
Classifier: License :: OSI Approved :: Zope Public License
